frappe_pre_commit-1.0.3.dist-info/licenses/LICENSE
scripts/__init__.py
scripts/check_coding_standards.py
scripts/check_doctype_naming.py
scripts/check_sql_security.py
frappe_pre_commit-1.0.3.dist-info/METADATA
frappe_pre_commit-1.0.3.dist-info/WHEEL
frappe_pre_commit-1.0.3.dist-info/entry_points.txt
frappe_pre_commit-1.0.3.dist-info/top_level.txt
frappe_pre_commit-1.0.3.dist-info/RECORD
