Metadata-Version: 2.4
Name: frappe-pre-commit
Version: 1.0.3
Summary: Pre-commit hooks for Frappe Framework coding standards
Author-email: Bhushan Barbuddhe <bhushan.barbuddhe@dhwaniris.com>
License-Expression: MIT
Project-URL: Homepage, https://github.com/dhwani-ris/frappe-pre-commit
Project-URL: Repository, https://github.com/dhwani-ris/frappe-pre-commit
Project-URL: Documentation, https://github.com/dhwani-ris/frappe-pre-commit#readme
Project-URL: Bug Tracker, https://github.com/dhwani-ris/frappe-pre-commit/issues
Project-URL: Changelog, https://github.com/dhwani-ris/frappe-pre-commit/blob/main/CHANGELOG.md
Keywords: frappe,erpnext,pre-commit,hooks,code-quality
Classifier: Development Status :: 4 - Beta
Classifier: Intended Audience :: Developers
Classifier: Operating System :: OS Independent
Classifier: Programming Language :: Python :: 3
Classifier: Programming Language :: Python :: 3.8
Classifier: Programming Language :: Python :: 3.9
Classifier: Programming Language :: Python :: 3.10
Classifier: Programming Language :: Python :: 3.11
Classifier: Topic :: Software Development :: Quality Assurance
Requires-Python: >=3.8
License-File: LICENSE
Requires-Dist: pyyaml>=6.0
Requires-Dist: click>=8.0
Dynamic: license-file
